{
    "Name": "KC.12",
    "Pitch": {
        "ALevel": 0,
        "ATime": 0,
        "DLevel": 0,
        "DTime": 0,
        "SLevel": 0,
        "STime": 0,
        "RLevel": 0,
        "RTime": 0
    },
    "OP1": {
        "Feedback": 0,
        "OP2In": 0,
        "OP3In": 0,
        "OP4In": 127,
        "Output": 127,
        "PitchEnv": 0,
        "Fixed": 0,
        "Ratio": 50,
        "Freq": 4402,
        "Detune": 0,
        "Level": 90,
        "VelSens": 100,
        "Time": 0,
        "UpCurve": 0,
        "DnCurve": 0,
        "Scale": 4,
        "ALevel": 127,
        "ATime": 0,
        "DLevel": 127,
        "DTime": 0,
        "SLevel": 0,
        "STime": 40,
        "RLevel": 0,
        "RTime": 80,
        "LGain": 0,
        "RGain": 0,
        "LCurve": 0,
        "RCurve": 0
    },
    "OP2": {
        "Feedback": -320,
        "OP1In": 0,
        "OP3In": 127,
        "OP4In": 0,
        "Output": 59,
        "PitchEnv": 0,
        "Fixed": 0,
        "Ratio": 50,
        "Freq": 4402,
        "Detune": 0,
        "Level": 124,
        "VelSens": 100,
        "Time": 0,
        "UpCurve": 0,
        "DnCurve": 0,
        "Scale": 4,
        "ALevel": 127,
        "ATime": 7,
        "DLevel": 80,
        "DTime": 0,
        "SLevel": 0,
        "STime": 92,
        "RLevel": 0,
        "RTime": 79,
        "LGain": 0,
        "RGain": 0,
        "LCurve": 0,
        "RCurve": 0
    },
    "OP3": {
        "Feedback": 630,
        "OP1In": 0,
        "OP2In": 0,
        "OP4In": 0,
        "Output": 0,
        "PitchEnv": 0,
        "Fixed": 0,
        "Ratio": 150,
        "Freq": 4402,
        "Detune": 43,
        "Level": 36,
        "VelSens": 100,
        "Time": 0,
        "UpCurve": 0,
        "DnCurve": 0,
        "Scale": 4,
        "ALevel": 127,
        "ATime": 22,
        "DLevel": 127,
        "DTime": 4,
        "SLevel": 23,
        "STime": 84,
        "RLevel": 0,
        "RTime": 80,
        "LGain": 0,
        "RGain": 0,
        "LCurve": 0,
        "RCurve": 0
    },
    "OP4": {
        "Feedback": 0,
        "OP1In": 0,
        "OP2In": 0,
        "OP3In": 0,
        "Output": 0,
        "PitchEnv": 0,
        "Fixed": 0,
        "Ratio": 50,
        "Freq": 4402,
        "Detune": 63,
        "Level": 40,
        "VelSens": 100,
        "Time": 0,
        "UpCurve": 0,
        "DnCurve": 0,
        "Scale": 4,
        "ALevel": 127,
        "ATime": 0,
        "DLevel": 127,
        "DTime": 0,
        "SLevel": 0,
        "STime": 58,
        "RLevel": 0,
        "RTime": 58,
        "LGain": 0,
        "RGain": 0,
        "LCurve": 0,
        "RCurve": 0
    },
    "Mixer": {
        "Level": 63
    }
}