{
    "Name": "RID.1",
    "Pitch": {
        "ALevel": 0,
        "ATime": 0,
        "DLevel": 0,
        "DTime": 0,
        "SLevel": 0,
        "STime": 0,
        "RLevel": 0,
        "RTime": 0
    },
    "OP1": {
        "Feedback": -630,
        "OP2In": 0,
        "OP3In": 127,
        "OP4In": 127,
        "Output": 127,
        "PitchEnv": 0,
        "Fixed": 0,
        "Ratio": 1000,
        "Freq": 4618,
        "Detune": 0,
        "Level": 50,
        "VelSens": 100,
        "Time": 0,
        "UpCurve": 0,
        "DnCurve": 3,
        "Scale": 3,
        "ALevel": 127,
        "ATime": 0,
        "DLevel": 84,
        "DTime": 0,
        "SLevel": 50,
        "STime": 0,
        "RLevel": 12,
        "RTime": 68,
        "LGain": 0,
        "RGain": 0,
        "LCurve": 0,
        "RCurve": 0
    },
    "OP2": {
        "Feedback": 0,
        "OP1In": 0,
        "OP3In": 127,
        "OP4In": 127,
        "Output": 127,
        "PitchEnv": 0,
        "Fixed": 0,
        "Ratio": 1200,
        "Freq": 4618,
        "Detune": 0,
        "Level": 45,
        "VelSens": 100,
        "Time": 0,
        "UpCurve": 0,
        "DnCurve": 3,
        "Scale": 3,
        "ALevel": 127,
        "ATime": 13,
        "DLevel": 84,
        "DTime": 81,
        "SLevel": 50,
        "STime": 101,
        "RLevel": 12,
        "RTime": 78,
        "LGain": 0,
        "RGain": 0,
        "LCurve": 0,
        "RCurve": 0
    },
    "OP3": {
        "Feedback": 0,
        "OP1In": 0,
        "OP2In": 0,
        "OP4In": 0,
        "Output": 0,
        "PitchEnv": 0,
        "Fixed": 0,
        "Ratio": 1400,
        "Freq": 4618,
        "Detune": 0,
        "Level": 70,
        "VelSens": 100,
        "Time": 0,
        "UpCurve": 0,
        "DnCurve": 3,
        "Scale": 3,
        "ALevel": 127,
        "ATime": 13,
        "DLevel": 84,
        "DTime": 81,
        "SLevel": 50,
        "STime": 102,
        "RLevel": 12,
        "RTime": 78,
        "LGain": 0,
        "RGain": 0,
        "LCurve": 0,
        "RCurve": 0
    },
    "OP4": {
        "Feedback": 590,
        "OP1In": 0,
        "OP2In": 0,
        "OP3In": 0,
        "Output": 0,
        "PitchEnv": 0,
        "Fixed": 0,
        "Ratio": 1600,
        "Freq": 4618,
        "Detune": 0,
        "Level": 115,
        "VelSens": 100,
        "Time": 0,
        "UpCurve": 0,
        "DnCurve": 3,
        "Scale": 3,
        "ALevel": 127,
        "ATime": 0,
        "DLevel": 51,
        "DTime": 81,
        "SLevel": 80,
        "STime": 120,
        "RLevel": 12,
        "RTime": 78,
        "LGain": 0,
        "RGain": 0,
        "LCurve": 0,
        "RCurve": 0
    },
    "Mixer": {
        "Level": 45
    }
}